undouble_gui/__init__.py
undouble_gui/examples.py
undouble_gui/gui.py
undouble_gui/undouble_gui.py
undouble_gui-0.1.0.dist-info/LICENSE
undouble_gui-0.1.0.dist-info/METADATA
undouble_gui-0.1.0.dist-info/WHEEL
undouble_gui-0.1.0.dist-info/top_level.txt
undouble_gui-0.1.0.dist-info/RECORD
