Metadata-Version: 2.1
Name: undouble_gui
Version: 0.1.0
Summary: Python package undouble_gui
Home-page: https://github.com/erdogant/undouble_gui
Download-URL: https://github.com/erdogant/undouble_gui/archive/0.1.0.tar.gz
Author: Erdogan Taskesen
Author-email: erdogant@gmail.com
Classifier: Programming Language :: Python :: 3
Classifier: License :: OSI Approved :: MIT License
Classifier: Operating System :: OS Independent
Requires-Python: >=3
License-File: LICENSE
Requires-Dist: clustimage
Requires-Dist: pillow
Requires-Dist: tkinter
